TarantoolLibrary.py
robotframework_tarantoollibrary-2.0.0.dist-info/LICENSE
robotframework_tarantoollibrary-2.0.0.dist-info/METADATA
robotframework_tarantoollibrary-2.0.0.dist-info/WHEEL
robotframework_tarantoollibrary-2.0.0.dist-info/top_level.txt
robotframework_tarantoollibrary-2.0.0.dist-info/RECORD
