Metadata-Version: 2.1
Name: robotframework-tarantoollibrary
Version: 2.0.0
Summary: A Robot Framework Tarantool Library
Home-page: https://github.com/peterservice-rnd/robotframework-tarantoollibrary
Author: JSC PETER-SERVICE
Author-email: MF_AIST_all@billing.ru
License: License :: OSI Approved :: Apache Software License
Platform: UNKNOWN
Classifier: Development Status :: 5 - Production/Stable
Classifier: Intended Audience :: Developers
Classifier: Topic :: Software Development :: Testing
Classifier: License :: OSI Approved :: Apache Software License
Classifier: Programming Language :: Python :: 3.6
Classifier: Framework :: Robot Framework :: Library
Requires-Dist: tarantool (>=0.5)
Requires-Dist: robotframework (>=3.0.2)
